quantrautil/__init__.py
quantrautil/qu.py
quantrautil/quantrautil.py
quantrautil-0.0.3.dist-info/LICENSE.txt
quantrautil-0.0.3.dist-info/METADATA
quantrautil-0.0.3.dist-info/WHEEL
quantrautil-0.0.3.dist-info/top_level.txt
quantrautil-0.0.3.dist-info/RECORD
