Metadata-Version: 2.1
Name: quantrautil
Version: 0.0.3
Summary: To fetch the data from web
Home-page: https://github.com/QuantInsti/Quantra-Courses/
Author: Quantra
Author-email: ishan.s@quantinsti.com
License: UNKNOWN
Platform: UNKNOWN
Classifier: Programming Language :: Python :: 3
Classifier: Programming Language :: Python :: 2.7
Classifier: Programming Language :: Python :: 3.6
Classifier: License :: OSI Approved :: MIT License
Classifier: Operating System :: OS Independent
Requires-Dist: fix-yahoo-finance (>=0.1.0)
Requires-Dist: nsepy (>=0.7)
Requires-Dist: iexfinance (>=0.4.1)
